{
  "animateLoading": true,
  "borderRadius": "1.5rem",
  "bottomRow": 4,
  "boxShadow": "0 10px 15px -3px rgba(0, 0, 0, 0.1), 0 4px 6px -2px rgba(0, 0, 0, 0.05)",
  "buttonColor": "{{appsmith.theme.colors.backgroundColor}}",
  "buttonVariant": "PRIMARY",
  "disabledWhenInvalid": false,
  "dynamicBindingPathList": [
    {
      "key": "buttonColor"
    }
  ],
  "dynamicPropertyPathList": [
    {
      "key": "onClick"
    }
  ],
  "dynamicTriggerPathList": [
    {
      "key": "onClick"
    }
  ],
  "iconAlign": "left",
  "iconName": "log-out",
  "isDefaultClickDisabled": true,
  "isDisabled": false,
  "isLoading": false,
  "isVisible": true,
  "key": "70n7y8edsm",
  "leftColumn": 40,
  "minWidth": 120,
  "mobileBottomRow": 31,
  "mobileLeftColumn": 7,
  "mobileRightColumn": 23,
  "mobileTopRow": 27,
  "needsErrorInfo": false,
  "onClick": "{{\nlogout.run(\n\t() => {\n\t\tremoveValue(\"accessToken\");\nremoveValue(\"currentUser\");\nshowAlert(\"Logout erfolgreich\", \"success\");\ngetMe.run();\nnavigateTo(\"LoginPage\")\n\t}\n)\n}}",
  "originalBottomRow": 69,
  "originalTopRow": 65,
  "parentColumnSpace": 6.84375,
  "parentId": "k5ly34aies",
  "parentRowSpace": 10,
  "placement": "CENTER",
  "recaptchaType": "V3",
  "renderMode": "CANVAS",
  "resetFormOnClick": false,
  "responsiveBehavior": "hug",
  "rightColumn": 62,
  "text": "Logout",
  "topRow": 0,
  "type": "BUTTON_WIDGET",
  "version": 1,
  "widgetId": "ab4nz2zft6",
  "widgetName": "btnLogoutCopy"
}